{
  "source": "github",
  "repository": "bitcoin/bips",
  "fetched_at": "2026-01-15T21:47:24.816422+00:00",
  "date": "2025-08-20",
  "pull_requests": [
    {
      "number": 1939,
      "title": "BIP85: replace Base64 by Base85 in PWD BASE85 section",
      "body": "Replace `Base64` by `Base85` encoder in the Pwd Base85 section, and use consistent capitalization.",
      "state": "closed",
      "user": "ethicnology",
      "created_at": "2025-08-20T13:45:30Z",
      "updated_at": "2025-08-21T15:49:23Z",
      "comments": 11,
      "url": "https://github.com/bitcoin/bips/pull/1939",
      "labels": [],
      "comment_list": [
        {
          "user": "akarve",
          "body": "@ethicnology in this spec the derived entropy, e.g. on both of the applications you commented on, is of fixed length. in what context would this be variable? there is trimming for the password length but that is explicitly post entropy. if you want truly variable password length and dictionaries (allows length of 1) maybe the new dice app is what you want? ",
          "created_at": "2025-08-20T18:28:46Z"
        },
        {
          "user": "akarve",
          "body": "@jonatack this particular change i'm asking for clarification on; so far i don't see the need. as for backward compatibility we now have a semver log. is it your opinion that even if the community adopts a major semver change that it needs to backward compatible or that said major semver change belongs in a clean BIP?",
          "created_at": "2025-08-20T18:30:49Z"
        },
        {
          "user": "jonatack",
          "body": "> as for backward compatibility we now have a semver log. is it your opinion that even if the community adopts a major semver change that it needs to backward compatible or that said major semver change belongs in a clean BIP?\r\n\r\nHi @akarve, yes, see https://github.com/bitcoin/bips/pull/1600#issuecomment-2394691135. I agree that breaking changes (if any) should first be discussed on the mailing list and with the projects that have already implemented the BIP, particularly for a BIP with final status, then probably go into a new BIP that replaces the previous one. Semver would be for non-breaking changes.",
          "created_at": "2025-08-20T19:05:12Z"
        },
        {
          "user": "akarve",
          "body": "> Hi @akarve, yes, see [#1600 (comment)](https://github.com/bitcoin/bips/pull/1600#issuecomment-2394691135).\r\n\r\nok this is a topic for another day. i’ll just point out that the situation leading to the above reasoning has since been addressed:\r\n\r\n> Furthermore, the BIPs process currently has no way to distinguish BIP versions and the way that has been implemented here is confusing.",
          "created_at": "2025-08-20T19:16:54Z"
        },
        {
          "user": "jonatack",
          "body": "> Furthermore, the BIPs process currently has no way to distinguish BIP versions and the way that has been implemented here is confusing.\r\n\r\nCould take a look at BIP3 and propose any improvements there you have in mind.",
          "created_at": "2025-08-20T19:29:37Z"
        },
        {
          "user": "scgbckbone",
          "body": "NACK\r\n\r\nit's always 64 bytes as it uses whole hmac-sha512 digest\r\n\r\n",
          "created_at": "2025-08-21T06:16:27Z"
        },
        {
          "user": "ethicnology",
          "body": "> it's always 64 bytes as it uses whole hmac-sha512 digest\r\n\r\nI understand, I was confused with the password length.\r\n\r\nI've amended my commit to replace only the Base64 by Base85 in the PWD BASE85 section",
          "created_at": "2025-08-21T11:35:31Z"
        },
        {
          "user": "scgbckbone",
          "body": "@ethicnology could you also unify capitalization on: `base64 -> Base64` & `base85 -> Base85`",
          "created_at": "2025-08-21T11:42:21Z"
        },
        {
          "user": "scgbckbone",
          "body": "ACK https://github.com/bitcoin/bips/pull/1939/commits/3e9befd44482acb8a13f40dfcd6fd9aec5d01a79",
          "created_at": "2025-08-21T12:15:43Z"
        },
        {
          "user": "jonatack",
          "body": "cc @akarve for feedback or sign-off",
          "created_at": "2025-08-21T15:38:29Z"
        },
        {
          "user": "akarve",
          "body": "Approved",
          "created_at": "2025-08-21T15:46:20Z"
        }
      ]
    }
  ],
  "issues": [],
  "summary": {
    "pull_requests": 1,
    "issues": 0
  }
}