{
  "source": "github",
  "repository": "bitcoin/bips",
  "fetched_at": "2026-01-15T21:45:30.799429+00:00",
  "date": "2025-08-02",
  "pull_requests": [
    {
      "number": 1910,
      "title": "BIP443: fix typo in the section \"Transaction-wide initialization\"",
      "body": "Itinitializes -> It initializes",
      "state": "closed",
      "user": "bethoffman",
      "created_at": "2025-08-02T10:34:43Z",
      "updated_at": "2025-08-05T22:40:32Z",
      "comments": 0,
      "url": "https://github.com/bitcoin/bips/pull/1910",
      "labels": [
        "Typo-to-be-collected"
      ]
    }
  ],
  "issues": [],
  "summary": {
    "pull_requests": 1,
    "issues": 0
  }
}